remapdict/__init__.py
remapdict-0.1.1.dist-info/LICENSE.txt
remapdict-0.1.1.dist-info/METADATA
remapdict-0.1.1.dist-info/WHEEL
remapdict-0.1.1.dist-info/top_level.txt
remapdict-0.1.1.dist-info/RECORD
